platon_rlp/__init__.py
platon_rlp/main.py
platon_rlp-1.2.0.dist-info/LICENSE
platon_rlp-1.2.0.dist-info/METADATA
platon_rlp-1.2.0.dist-info/WHEEL
platon_rlp-1.2.0.dist-info/top_level.txt
platon_rlp-1.2.0.dist-info/RECORD
